{
  "city.property.info": "§sUUID: §r§7{0} \n§sIsle: §r§7{1} \n§sOwner: §r§7{2} \n§sHelpers: §r§7{3} \n§sAdded: §r§7{4} \n§sBlocked: §r§7{5} \n§sSettings: §r§7{6} \n",
  "city.property.info.player": " - §7{0}",
  "city.property.info.setting": " - §s{0}: §r§7{1}",
  "city.property.info.title": "Info",
  "city.notonproperty": "You are not standing on a plot!",
  "city.flags.pvp.name": "PvP",
  "city.flags.type.name": "Plot Type",
  "city.clearproperty.confirm": "Use /p clear confirm to proceed",
  "city.clearproperty.success": "Your plot has been successfully cleared.",
  "city.notenoughshards": "You do not have enough Shards",
  "city.notowner": "You do not own this plot!",
  "city.property.claim.accept": "Accept Offer",
  "city.property.claim.already_claimed": "This plot already has an owner",
  "city.property.claim.description": "Would you like to rent this plot for {0} Shards / {1} days?",
  "city.property.claim.success": "You have successfully accepted the offer.",
  "city.property.claim.title": "Rent Plot",
  "city.property.search.content": "Please select a plot type",
  "city.property.search.no_free_property": "There are no free plots of this type on this isle!",
  "city.property.search.success": "The nearest free plot of this type is located at {0} {1} {2}",
  "city.property.search.title": "Plot Search",
  "city.property.set.invalidflag": "This setting does not exist",
  "city.property.set.invalidvalue": "Please provide a valid value",
  "city.property.set.success": "You have successfully changed this setting!",
  "city.property.set.usage": "/p set <setting> <value>",
  "city.propertynoowner": "This plot has no owner",
  "city.rentalalreadypaid": "The rent has already been paid",
  "city.rentpaid": "You have successfully paid the rent.",
  "city.resetproperty.confirm": "Use /p reset confirm to proceed",
  "city.resetproperty.success": "Your plot has been successfully reset and released.",
  "isle.switch.content": "Please select an isle",
  "isle.switch.title": "Switch Isle",
  "property.list.at": "The selected plot is located at {0} {1} {2}",
  "property.list.button": "Plot {0} {1}",
  "property.list.content": "Please select a plot",
  "property.list.empty": "You do not have access to any plots.",
  "property.list.title": "Plot List",
  "city.bank.account.create.max": "§cYou have already reached the maximum number of bank accounts and cannot create another one.",
  "city.bank.account.created": "§aYou have successfully created a new bank account.",
  "city.bank.account.members.add.max": "§cThe maximum number of members has been reached.",
  "city.bank.account.members.add.self": "§cYou cannot add yourself to your own bank account.",
  "city.bank.deposit": "§e{0} §7deposited §u{1} Shards §7into the bank account.",
  "city.bank.deposit.invalidamount": "§cThe deposit amount is invalid. Please enter a valid number greater than 0.",
  "city.bank.deposit.notenough": "§cYou do not have enough Shards to deposit the specified amount.",
  "city.bank.form.account.button.deposit": "Deposit",
  "city.bank.form.account.button.members": "Members",
  "city.bank.form.account.button.remove": "§cLeave Account",
  "city.bank.form.account.button.transfer": "Transfer",
  "city.bank.form.account.button.withdraw": "Withdraw",
  "city.bank.form.account.content": "§7Account ID: §e{0} \n§7Shards: §u{1}",
  "city.bank.form.account.deposit.element.info": "§7You currently have §u{0} Shards§7.",
  "city.bank.form.account.members.add": "Add Member",
  "city.bank.form.account.members.add.element.info": "§cEach member has access to the entire bank account. The account currently holds §u{0} Shards§c.",
  "city.bank.form.account.members.content": "§7Select a member or add a new one.",
  "city.bank.form.account.transfer.element.info": "§7The bank account currently holds §u{0} Shards§7.",
  "city.bank.form.account.withdraw.element.info": "§7The bank account currently holds §u{0} Shards§7.",
  "city.bank.form.button.account": "§rAccount #{0}§r\n§7Shards: §u{1} §8| §7Members: §e{2}",
  "city.bank.form.button.create": "New Bank Account",
  "city.bank.form.content": "§7Please select an option or a bank account.",
  "city.bank.form.title": "Bank",
  "city.bank.member.add.other": "§e{0} §7invited §e{1} §7to the bank account.",
  "city.bank.member.add.self": "§7You have been added to the bank account.",
  "city.bank.member.leave.other": "§e{0} §7has left the bank account.",
  "city.bank.member.leave.self": "§aYou have left bank account §e{0}§a.",
  "city.bank.transfer.invalidamount": "§cPlease enter a valid number.",
  "city.bank.withdraw.invalidamount": "§cThe withdrawal amount is invalid. Please enter a valid number greater than 0.",
  "city.bank.withdraw.notenough": "§cThe bank account does not have enough Shards to withdraw the specified amount.",
  "city.bank.withdrawn": "§e{0} §7withdrew §u{1} Shards §7from the bank account.",
  "city.council.form.begin.title": "§l§2Town Hall",
  "city.council.form.begin.content": "§7Welcome to the Town Hall! \n§7Please select a matter.",
  "city.council.form.begin.idcard.renew": "Renew ID Card",
  "city.council.form.begin.idcard.lost": "Lost ID Card",
  "city.council.dialog.welcome": "Good day, how may I help you?",
  "city.council.dialog.busy": "Can you not see that I am busy?",
  "city.council.dialog.comelater": "Please come back later.",
  "city.council.dialog.idcard.renew.lookup": "Thank you, let me just check the system...",
  "city.council.dialog.idcard.renew.tooearly": "I'm afraid I cannot renew this ID card yet — renewal is only possible within 3 days of expiry.",
  "city.council.dialog.idcard.renew.end1": "Please take your ID card with you. Goodbye.",
  "city.council.dialog.idcard.renew.notyouridcard": "But this ID card has a different name on it...",
  "city.council.dialog.idcard.renew.end2": "Please take this ID card with you. Goodbye.",
  "city.council.dialog.idcard.renew.raw.1": "Oh, a blank card — where did you get that?",
  "city.council.dialog.idcard.renew.raw.2": "I'll hold on to that. Have a nice day.",
  "city.council.dialog.idcard.renew.wrongitem": "That is not an ID card.",
  "city.council.dialog.idcard.renew.wrongitem2": "Please place an ID card on the counter!",
  "city.council.dialog.idcard.renew.begin.1": "Ah, I see...",
  "city.council.dialog.idcard.renew.pleaseinsert": "Please place your ID card in the frame",
  "city.council.dialog.idcard.renew.renewed": "I will now extend your ID card by another 3 months...",
  "city.bank.account.members.add.alreadymember": "§The player §e{0} §cis already a member of this bank account.",
  "city.bank.account.notexists": "§cThis bank account does not exist.",
  "city.bank.content": "§7Select an action to continue",
  "city.bank.form.account.transfer.content": "§7Select a bank account:",
  "city.bank.form.delete.title": "§l§cDelete Bank Account",
  "city.bank.transfer.notenough": "§cThis bank account does not have enough Shards for this transfer.",
  "city.commands.invsee.args": "/invsee <player> [type]",
  "city.commands.invsee.invtype.invalid": "§cThe inventory type is invalid.",
  "city.commands/invsee.own": "§cYou cannot view your own inventory.",
  "city.council.dialog.idcard.renew.invalid.1": "Oh, this is not a valid ID card!",
  "city.council.dialog.idcard.renew.invalid.2": "I'm afraid I will have to keep this. Have a nice day.",
  "city.council.idcard.lost.pricing.accept": "§aAccept Offer §7({0} Shards)",
  "city.council.idcard.lost.pricing.content": "§7Replacing a lost ID card costs {0} Shards. \n§7Would you like to request a new ID card?",
  "city.council.idcard.lost.pricing.decline": "§cDecline Offer",
  "city.council.idcard.lost.pricing.title": "§l§2Request New ID Card",
  "city.elevator.private": "§cThis elevator is private.",
  "city.feed.fed": "§aYou have been successfully fed.",
  "city.fix.chunks": "§e{0} chunks §7have been successfully repaired.",
  "city.fix.inv": "§aYour inventory has been successfully repaired.",
  "city.heal.healed": "§aYou have been successfully healed.",
  "city.idcard.form.title": "§l§2ID Card",
  "city.inventory.clear.player.success": "§aYour inventory has been successfully cleared.",
  "city.inventory.form.clear.content": "§7Are you sure you want to clear your inventory? \n§7This cannot be undone.",
  "city.inventory.form.clear.title": "§l§cClear Inventory",
  "city.inventory.form.clear.yes.clear": "§aYes, Clear Inventory",
  "city.inventory.session.max": "§cYou have reached the maximum number of inventory sessions.",
  "city.jobs.menu.content.employed": "§7Select a job to continue. \n§7Current job: §e{0}",
  "city.jobs.menu.content.unemployed": "§7Select a job to continue. \n§7You are currently unemployed.",
  "city.jobs.menu.title": "Jobs",
  "city.jobs.jobbtn": "§3{0}\n§o§bLevel {1} ({2}/{3} XP)",
  "city.job.miner": "Miner",
  "city.job.logger": "Lumberjack",
  "city.job.hunter": "Hunter",
  "city.job.chef": "Chef",
  "city.job.fisher": "Fisher",
  "city.job.waste_collector": "Garbage Collector",
  "city.location.unsafe.single": "§cThe requested location is not safe.",
  "city.property.add.description": "§7Would you like to add {0} as a helper or as a trusted person?",
  "city.property.add.helper.success": "§e{0} §ahas been successfully added as a helper.",
  "city.property.add.title": "§l§2Add Player",
  "city.property.add.trusted.success": "§e{0} §ahas been successfully added as a trusted person.",
  "city.property.add.type": "§7Please select a type:",
  "city.property.add.usage": "/p add",
  "city.property.creation.already": "§cYou are already creating a plot.",
  "city.property.creation.created": "§aThe plot has been successfully created.",
  "city.property.creation.creating": "§7Creating plot...",
  "city.property.creation.pos2": "§7Set the second position.",
  "city.property.creation.start": "§7Set the first position.",
  "city.property.data.number": "§aPlot number set: §r§7{0}",
  "city.property.data.street": "§aStreet set: §r§7{0}",
  "city.property.data.usage": "/p data <street|number> <value>",
  "city.property.deniedremoved": "§e{0} §ais no longer blocked.",
  "city.property.deny.success": "§e{0} §ahas been successfully blocked.",
  "city.property.helperremoved": "§e{0} §ais no longer a helper.",
  "city.property.popup.owned": "§l§f{0} {1}\n§r§7Owner: §e{2}",
  "city.property.popup.unowned": "§l§f{0} {1}\n§r§aAvailable",
  "city.property.remove.denied": "{0} \n§o§cBlocked",
  "city.property.remove.description": "Select a player and their status to remove.",
  "city.property.remove.helper": "{0} \n§o§bHelper",
  "city.property.remove.title": "§l§cRemove Player",
  "city.property.remove.trusted": "{0} \n§o§dTrusted",
  "city.property.trustedremoved": "§e{0} §ais no longer a trusted person.",
  "city.scoreboard.title": "§l§6Scoreboard",
  "city.scoreboard.top": "Small Scoreboard",
  "city.tashcan.admin.clear": "§l§c[ADMIN] Empty Trash Can",
  "city.trashcan.admin.maxitems": "§7Maximum number of items that fit in the trash can.",
  "city.trashcan.admin.setmax": "§l§c[ADMIN] Set Maximum Item Count",
  "city.trashcan.collect": "§fEmpty Trash Can",
  "city.trashcan.content": "§7Select an action to continue",
  "city.trashcan.title": "§l§6Trash Can",
  "city.wallet.title": "Wallet",
  "city.council.dialog.idcard.lost.begin": "Oh, you have lost your ID card?",
  "city.council.dialog.idcard.lost.offer.declined": "What a shame. Have a nice day.",
  "city.council.dialog.idcard.lost.price": "A new ID card costs {0} Shards.",
  "city.property.type.none": "Unknown",
  "city.property.type.apartment": "Apartment",
  "city.property.type.property": "Plot",
  "city.property.type.land": "Land",
  "city.chestshop.create.invaliditem": "§cThis item is invalid.",
  "city.chestshop.create.invalidplacement": "§cYou cannot create a chest shop here.",
  "city.chestshop.create.success": "§aYou have successfully created a chest shop.",
  "city.chestshop.handle.invalidamount": "§cThe shop has an invalid item quantity, so the action could not be completed.",
  "city.chestshop.handle.invaliditem": "§cThe shop has an invalid item, so the action could not be completed.",
  "city.chestshop.handle.invalidowner": "§cThe owner of this chest shop is invalid, so the action could not be completed.",
  "city.chestshop.handle.invalidprice": "§cThe shop has an invalid price, so the action could not be completed.",
  "city.isle.allowsflyset": "Fly mode has been changed!",
  "city.isle.explorableset": "Explorable setting has been changed!",
  "city.isle.harbornpcset": "Harbor NPC setting has been changed!",
  "city.isle.permissionset": "Isle permission has been changed!",
  "city.notonplot.own": "§cYou are not standing on your own plot!",
  "city.shopfinder.form.button.back": "Back",
  "city.shopfinder.form.button.next": "Next",
  "city.shopfinder.form.button.shop": "{0} \n§7{1} Visitors §8| §e{2} Stars",
  "city.shopfinder.form.shop.button.rate": "Rate Shop",
  "city.shopfinder.form.shop.button.teleport": "Teleport to Shop",
  "city.shopfinder.form.shop.content": "§fName: §e{0} \n§fType: §e{1} \n§fVisitors: §e{2} \n§fRating: §e{3} Stars \n\n§7Please select an option.",
  "city.shopfinder.form.shop.manage.button.categories.add": "Add Category",
  "city.shopfinder.form.shop.manage.button.categories.remove": "Remove Category",
  "city.shopfinder.form.shop.manage.button.delete": "Delete Shop Listing",
  "city.shopfinder.form.shop.manage.button.relocate": "Relocate Shop",
  "city.shopfinder.form.shop.manage.button.type": "Change Shop Type",
  "city.shopfinder.form.shop.manage.name": "Rename Shop",
  "city.shopfinder.form.shop.manage.type.content": "Select an action you would like to perform.",
  "city.shopfinder.form.shop.rate.element.label.info": "Please rate the shop with 1–10 stars. \n\n0 stars or fewer will be counted as 1 star. \n11 stars or more will be counted as 10 stars.",
  "city.shopfinder.shop.category.minimum": "You must have at least one category set for your shop.",
  "city.shopfinder.shop.category.remove": "§aCategory §e{0} §ahas been removed from your shop.",
  "city.shopfinder.shop.name.empty": "Please enter a name",
  "city.shopfinder.shop.name.invalidregex": "Your shop name contains invalid characters.",
  "city.shopfinder.shop.name.maxlength": "Your shop name may be at most 10 characters long.",
  "city.shopfinder.shop.relocated": "You have successfully relocated your shop.",
  "city.shopfinder.shop.renamed": "You have successfully renamed your shop.",
  "city.shopfinder.shop.type.set": "You have successfully changed the type of your shop.",
  "city.shopfinder.title": "§l§6Shop Finder",
  "city.trashcan.admin.clear": "§c[ADMIN] Empty Trash Can",
  "city.chestshop.buy.chest.notenough": "§cThis shop does not have enough items.",
  "city.chestshop.buy.notenough": "§cYou do not have enough Shards",
  "city.chestshop.buy.other": "§e{0} §7purchased §e{1}x {2} §7from your chest shop.",
  "city.chestshop.buy.self": "§7You have successfully purchased §e{0}x {1}§7.",
  "city.chestshop.create.invalidamount": "Please enter a valid quantity.",
  "city.chestshop.create.invalidprice": "Please enter a valid price.",
  "city.chestshop.form.create.element.label.price.info": "§7You can check the current market value with §e/marketvalue§7.",
  "city.chestshop.form.title": "Chest Shop",
  "city.chestshop.handle.own": "You cannot buy from your own shop.",
  "city.chestshop.sell.item.notenough": "§cThe shop currently does not have enough items.",
  "city.chestshop.sell.owner.notenough": "§cThe owner of this chest shop does not have enough §uShards§c to pay you.",
  "city.chestshop.sell.self": "§7You have successfully sold §e{0}x {1}§7.",
  "city.clearlag.chat": "§7All items and entities will be removed in §b{0}§7.",
  "city.clearlag.done": "§7§e{0} entities §7were removed and §e{1} chunks §7were unloaded.",
  "city.clearlag.issued": "§l§mWarning",
  "city.clearlag.subtitle": "§l§cAll items and entities have been removed.",
  "city.clearlag.subtitle.issued": "§r§cAll items and entities will be removed in §b5 seconds§c.",
  "city.clearlag.time": "§7The next clearlag will occur in §b{0}§7.",
  "city.clearlag.tip": "§7All items and entities will be removed in §b{0}§7.",
  "city.clearlag.title": "§l§4Warning",
  "city.mv.form.button": "{0}\n1x §u{1} Shards",
  "city.mv.form.button.search": "Search for an Item",
  "city.mv.form.content": "§7Page §e{0} §7of §e{1} §8| §e{2} §7Items \n§7Select an item.",
  "city.mv.form.item.label.calculate": "§7Calculate Price \n§7§oPlease select a quantity",
  "city.mv.form.item.content": "§e{0} §7- §u{1} Shards",
  "city.mv.form.search.element.label.info": "§7Please enter an item name or ID.",
  "city.mv.form.title": "Market Value",
  "city.mv.noentries": "§cNo entries found.",
  "city.mv.price": "§7The market value for §e{0}x {1} §7is §u{2} Shards§7.",
  "city.shopfinder.create.max": "§cYou cannot register any more shops in the shop finder.",
  "city.shopfinder.create.success": "§7You have successfully registered your shop §e{0} §7in the shop finder.",
  "city.shopfinder.form.button.create": "Register New Shop",
  "city.shopfinder.form.button.own": "Your Shops",
  "city.shopfinder.form.button.search": "Search for Shop",
  "city.shopfinder.form.content": "§7Please select an option or a shop.",
  "city.shopfinder.form.element.dropdown.category": "Shop Category",
  "city.shopfinder.form.element.dropdown.type": "Shop Type",
  "city.shopfinder.form.own.content": "§7Please select one of your shops to manage it, or create a new shop.",
  "city.shopfinder.form.search.content": "§7§e{0} §7shops were found.",
  "city.shopfinder.form.search.content.empty": "§cNo shop was found matching your search criteria.",
  "city.shopfinder.form.title": "Shop Search",
  "city.shopfinder.name.empty": "§cPlease enter a name",
  "city.shopfinder.name.invalidregex": "§cPlease enter a valid name.",
  "city.shopfinder.name.maxlength": "§cYour shop name may be at most 10 characters long.",
  "city.shopfinder.shop.category.add": "§7You have added category §e{0} §7to your shop.",
  "city.shopfinder.shop.deleted": "§7You have deleted your shop §e{0}§7.",
  "city.shopfinder.shop.rate.invalidrating": "§cPlease provide a valid rating.",
  "city.shopfinder.shop.rate.success": "§7You have successfully rated the shop with §e{0} §7stars.",
  "city.scoreboard.isle": "Isle",
  "city.scoreboard.line.0": "First Entry",
  "city.scoreboard.line.1": "Second Entry",
  "city.scoreboard.line.2": "Third Entry",
  "city.scoreboard.line.3": "Fourth Entry",
  "city.flags.pve.name": "PvE",
  "city.flags.damage.name": "Damage",
  "city.flags.rent.name": "Rent",
  "city.flags.rent_paid_date.name": "Rent Paid On",
  "city.flags.rent_next_due.name": "Next Rent Due",
  "city.flags.rent_period_days.name": "Rent Period (Days)",
  "city.flags.default_player_perm.name": "Default Player Permission",
  "city.flags.show_actionbar.name": "Info on Enter",
  "property.command.admin.select.success": "§aYou have successfully selected the plot.",
  "city.property.creation.expanded": "§aThe plot has been successfully expanded.",
  "property.command.admin.deselect.success": "§aYou have successfully deselected the plot.",
  "property.command.admin.cubes.noselected": "§cNo plot has been selected.",
  "property.command.admin.select.noproperty": "§cPlease select a plot first.",
  "city.job.none": "Unemployed",
  "isle.type.reg": "Government Isle",
  "isle.type.perl": "SOON",
  "isle.type.farm": "Farm World",
  "city.inventories.inv": "Player Inventory",
  "city.auction.title": "Auction House",
  "city.auction.content": "Browse current auctions",
  "city.auction.button.create": "Create Auction",
  "city.auction.button.mine": "My Auctions",
  "city.auction.button.claims": "Collections",
  "city.auction.listing": "{0} x{1}",
  "city.auction.listing.bid": "§bBid: §e{0}",
  "city.auction.listing.buyout": "§bBuy Now: §e{0}",
  "city.auction.listing.time": "§bTime: §e{0}",
  "city.auction.create.title": "Create Auction",
  "city.auction.create.item": "Item: {0} x{1}",
  "city.auction.create.amount": "Quantity",
  "city.auction.create.startprice": "Starting Price (Shards)",
  "city.auction.create.buyout": "Buy Now Price (optional)",
  "city.auction.create.duration": "Duration (Minutes)",
  "city.auction.create.holditem": "Hold the item you want to auction in your hand.",
  "city.auction.create.invalidamount": "Invalid quantity.",
  "city.auction.create.startprice.invalid": "The starting price must be positive.",
  "city.auction.create.buyout.invalid": "The buy now price must be >= the starting price.",
  "city.auction.create.duration.invalid": "The duration must be between {0} and {1} minutes.",
  "city.auction.create.remove.failed": "The item could not be removed from your inventory.",
  "city.auction.create.success": "Auction created.",
  "city.auction.detail.title": "Auction",
  "city.auction.detail.item": "§bItem: §e{0} x{1}",
  "city.auction.detail.seller": "§bSeller: §e{0}",
  "city.auction.detail.bid": "§bCurrent Bid: §e{0} Shards",
  "city.auction.detail.buyout": "§bBuy Now: §e{0}",
  "city.auction.detail.time": "§bTime Remaining: §e{0}",
  "city.auction.button.bid": "Place Bid",
  "city.auction.button.buyout": "Buy Now",
  "city.auction.button.cancel": "Cancel Auction",
  "city.auction.button.claim": "Collect Item",
  "city.auction.bid.title": "Place Bid",
  "city.auction.bid.amount": "Bid (Shards)",
  "city.auction.bid.ended": "This auction has ended.",
  "city.auction.bid.own": "You cannot bid on your own auction.",
  "city.auction.bid.low": "Your bid must be higher than the current bid.",
  "city.auction.bid.placed": "Your bid has been placed.",
  "city.auction.cancel.bids": "Auctions with bids cannot be cancelled.",
  "city.auction.cancel.success": "Auction cancelled. You can collect your item.",
  "city.auction.claim.denied": "You cannot collect this item.",
  "city.auction.claim.full": "Your inventory is full.",
  "city.auction.claim.success": "Item collected.",
  "city.auction.claim.menu.title": "Collections",
  "city.auction.claim.menu.content": "Collect auction winnings and returns",
  "city.auction.claim.menu.empty": "No items available for collection.",
  "city.auction.claim.menu.claimall": "Collect All",
  "city.auction.claim.menu.claimall.desc": "Collect all available items",
  "city.auction.claim.menu.info": "Click for details",
  "city.auction.claim.status.won": "§bWon: §e{0} Shards",
  "city.auction.claim.status.unsold": "§bUnsold",
  "city.auction.claim.info.title": "Item Info",
  "city.auction.claim.info.nolore": "§7No description",
  "city.auction.claim.info.price": "§bPrice: §e{0} Shards",
  "city.auction.claim.info.unsold": "§7No buyer found",
  "city.auction.claim.menu.claim": "Collect Item",
  "city.auction.claim.menu.relist": "Relist",
  "city.auction.relist.denied": "This item cannot be relisted.",
  "city.auction.relist.success": "Auction relisted.",
  "city.auction.buyout.seller": "Your auction has been purchased via Buy Now.",
  "city.auction.my.title": "My Auctions",
  "city.auction.my.content": "Your active and ended auctions",
  "city.auction.my.listing": "{0} x{1} | {2}",
  "city.auction.time.ended": "Ended",
  "city.bank.form.account.button.actions": "Actions",
  "city.bank.form.account.transfer.element.note": "Note (optional)",
  "city.bank.account.members.add.success": "§aMember added: §e{0}",
  "city.bank.deposit.success": "§aDeposit completed: §e{0}§a Shards to §e{1}§a.",
  "city.bank.withdraw.success": "§aWithdrawal completed: §e{0}§a Shards from §e{1}§a.",
  "city.bank.transfer.success": "§aTransfer completed: §e{0}§a Shards to §e{1}§a.",
  "city.bank.transfer.self": "§e{0} §7transferred §u{1} Shards §7to bank account §e{2}§7.",
  "city.bank.transfer.other": "§e{0} §7transferred §u{1} Shards §7from bank account §e{2} §7to this account.",
  "city.bank.admin.title": "Bank Administration",
  "city.bank.admin.content": "§7Select an option.",
  "city.bank.admin.select.id": "Select Account by ID",
  "city.bank.admin.select.player": "Select Account by Player",
  "city.bank.admin.input.id": "Account Number",
  "city.bank.admin.account.title": "Bank Administration #{0}",
  "city.bank.admin.action.deposit": "§rDeposit",
  "city.bank.admin.action.withdraw": "§rWithdraw",
  "city.bank.admin.action.transfer": "§rTransfer",
  "city.bank.admin.action.delete": "§cDelete Account",
  "city.bank.admin.member.remove.title": "§l§cRemove Member",
  "city.bank.admin.member.remove.content": "§7Are you sure you want to remove §e{0} §7from the bank account?",
  "city.bank.admin.member.remove.success": "§aMember removed: §e{0}",
  "city.bank.admin.delete.content": "§7Are you sure you want to delete bank account §e{0}§7?",
  "city.bank.admin.delete.success": "§aBank account §e{0} §adeleted.",
  "city.bank.member.remove.other": "§e{0} §7removed §e{1} §7from the bank account.",
  "city.bank.account.deleted.other": "§e{0} §7has deleted the bank account.",
  "city.bank.action.account.title": "Actions #{0}",
  "city.bank.action.content": "Recent Actions",
  "city.bank.action.listing.sent": "Sent {0} Shards - {1}",
  "city.bank.action.listing.received": "Received {0} Shards - {1}",
  "city.bank.action.listing.deposit": "Deposit {0} Shards",
  "city.bank.action.listing.withdraw": "Withdrawal {0} Shards",
  "city.bank.action.listing.member": "Member Action - {0}",
  "city.bank.action.listing.system": "System - {0}",
  "city.bank.action.listing.admin": "Admin - {0}",
  "city.bank.action.listing.automated": "Automated - {0}",
  "city.bank.action.detail.title": "Action",
  "city.bank.action.detail.type": "§bType: §e{0}",
  "city.bank.action.type.transfer": "Transfer",
  "city.bank.action.type.deposit": "Deposit",
  "city.bank.action.type.withdraw": "Withdrawal",
  "city.bank.action.type.member": "Member Management",
  "city.bank.action.type.system": "System",
  "city.bank.action.type.admin": "Admin",
  "city.bank.action.type.automated": "Automated",
  "city.bank.action.detail.actor": "§bAction by: §e{0}",
  "city.bank.action.detail.from": "§bFrom: §e{0}",
  "city.bank.action.detail.to": "§bTo: §e{0}",
  "city.bank.action.detail.amount": "§bAmount: §e{0} Shards",
  "city.bank.action.detail.date": "§bDate: §e{0}",
  "city.bank.action.detail.note": "§bNote:\n§r{0}",
  "city.bank.action.detail.item": "§bItem: §e{0} x{1}",
  "city.auction.time.minutes": "Minutes",
  "city.farmitems.community.finished": "§aThe community task has been completed.",
  "city.farmitems.community.thanks": "§aThank you! You submitted §e{0}x {1} §aand received §u{2} Shards§a.",
  "city.farmitems.menu.btn.communityitems": "Community Items\n§7{0}x {1} §8| §u{2} Shards",
  "city.farmitems.menu.content": "§7Select a task.",
  "city.farmitems.menu.title": "Farm Items",
  "city.homes.form.content": "§7Select a home.",
  "city.homes.form.home.button.relocate": "Relocate",
  "city.homes.form.home.button.remove": "§cRemove",
  "city.homes.form.home.button.rename": "Rename",
  "city.homes.form.home.button.teleport": "Teleport",
  "city.homes.form.home.content": "§7Isle: §e{0}\n§7Position: §e{1}",
  "city.homes.set": "§aHome §e{0} §ahas been set.",
  "city.homes.set.cannotrelocate": "§cYou cannot relocate this home.",
  "city.homes.teleporting": "§aTeleporting to §e{0}§a...",
  "city.jobs.changed": "§aYour job has been changed to §e{0}§a.",
  "city.property.rent.unpaid.owner": "§cThe rent for your plot has not been paid.",
  "city.shop.category.admin": "Admin",
  "city.shop.category.armor": "Armor",
  "city.shop.category.building": "Building",
  "city.shop.category.end": "The End",
  "city.shop.category.mobdrops": "Mob Drops",
  "city.shop.category.nether": "Nether",
  "city.shop.category.ores": "Ores",
  "city.shop.category.overworld": "Overworld",
  "city.shop.category.tools": "Tools",
  "city.shop.type.chestshop": "Chest Shop",
  "city.shop.type.store": "Shop",
  "cb/clearlag.broadcast": "§7All items and entities will be removed in §b{0}§7.",
  "cb/clearlag.done": "§7§e{0} entities §7were removed and §e{1} chunks §7were unloaded.",
  "cb/clearlag.tip": "§7Clearlag in §b{0}§7.",
  "city.fly.admin.added": "§a§e{0} §ahas been given §e{1} §aflight time.",
  "city.fly.admin.example": "30",
  "city.fly.admin.input": "Minutes",
  "city.fly.admin.invalid": "§cPlease enter a valid number of minutes.",
  "city.fly.admin.title": "Grant Flight Time",
  "city.fly.disabled": "§cYour fly mode has been disabled.",
  "city.fly.enabled": "§aYou can now fly!",
  "city.fly.expired": "§cYour flight time has expired.",
  "city.fly.no_time": "§cYou have no flight time remaining.",
  "city.fly.shop.admin": "§7You have unlimited flight time.",
  "city.fly.shop.content": "§7Current flight time: §e{0}",
  "city.fly.shop.notenough": "§cYou do not have enough items.",
  "city.fly.shop.offer": "§b{0}x {1}\n§7+ §e{2}",
  "city.fly.shop.success": "§aYou have received §e{0} §aflight time.",
  "city.fly.shop.title": "Flight Time",
  "city.economy.audit.title": "§l§6Economy Audit",
  "city.economy.audit.content": "§7Select a view.",
  "city.economy.audit.button.latest": "Latest Entries",
  "city.economy.audit.button.player": "By Player",
  "city.economy.audit.button.bank": "By Bank Account",
  "city.economy.audit.empty": "§7No entries found.",
  "city.economy.audit.bank.input": "Bank Account ID",
  "city.economy.audit.bank.invalid": "§cPlease enter a valid bank account ID.",
  "city.economy.audit.list.title": "§l§6Economy Audit",
  "city.economy.audit.list.content": "§7Page §e{0}§7/§e{1}",
  "city.economy.audit.list.entry": "§bAction: §e{0}\n§7From: §e{1} §8| §7To: §e{2}\n§7Amount: §u{3} §8| §7Time: §e{4}",
  "city.economy.audit.detail.title": "§l§6Audit Details",
  "city.economy.audit.detail.type": "§bAction: §e{0}",
  "city.economy.audit.detail.amount": "§bAmount: §e{0} §7({1})",
  "city.economy.audit.detail.actor": "§bPerformed by: §e{0}",
  "city.economy.audit.detail.target": "§bTarget: §e{0}",
  "city.economy.audit.detail.from": "§bFrom Account: §e{0}",
  "city.economy.audit.detail.to": "§bTo Account: §e{0}",
  "city.economy.audit.detail.source": "§bSource: §e{0}",
  "city.economy.audit.detail.isle": "§bIsle: §e{0}",
  "city.economy.audit.detail.date": "§bTime: §e{0}",
  "city.economy.audit.detail.item": "§bItem: §e{0}",
  "city.economy.audit.detail.description": "§bDescription: §e{0}",
  "city.economy.audit.detail.note": "§bNote: {0}",
  "city.economy.audit.type.bank_deposit": "Bank Deposit",
  "city.economy.audit.type.bank_withdraw": "Bank Withdrawal",
  "city.economy.audit.type.bank_transfer": "Bank Transfer",
  "city.economy.audit.type.bank_admin": "Bank Admin",
  "city.economy.audit.type.bank_system": "Bank System",
  "city.economy.audit.type.bank_automated": "Bank Automated",
  "city.economy.audit.type.shopfinder_fee": "Shop Finder Fee",
  "city.economy.audit.type.chestshop_buy": "Chest Shop Purchase",
  "city.economy.audit.type.chestshop_sell": "Chest Shop Sale",
  "city.economy.audit.type.property_claim": "Plot Rental",
  "city.economy.audit.type.property_rent": "Plot Rent Paid",
  "city.economy.audit.type.job_reward": "Job Payout",
  "city.economy.audit.type.farm_reward": "Farm Payout",
  "city.economy.audit.type.auction_list": "Auction Listed",
  "city.economy.audit.type.auction_bid": "Auction Bid",
  "city.economy.audit.type.auction_refund": "Auction Refund",
  "city.economy.audit.type.auction_payout": "Auction Payout",
  "city.economy.audit.type.auction_claim_item": "Auction Item Collected",
  "city.economy.audit.type.auction_return_item": "Auction Item Returned",
  "city.economy.audit.type.player_pay": "Player Payment",
  "city.economy.audit.type.player_request": "Payment Requested",
  "city.economy.audit.type.player_request_paid": "Payment Fulfilled",
  "city.pay.title": "§l§6Pay",
  "city.pay.amount": "Amount",
  "city.pay.note": "Note (optional)",
  "city.pay.invalidamount": "§cPlease enter a valid amount.",
  "city.pay.notenough": "§cYou do not have enough Shards.",
  "city.pay.sent": "§aYou have transferred §u{0} Shards §ato §e{1}§a.",
  "city.pay.received": "§e{0} §7sent you §u{1} Shards§7.",
  "city.request.title": "§l§6Request Payment",
  "city.request.amount": "Amount",
  "city.request.note": "Note (optional)",
  "city.request.invalidamount": "§cPlease enter a valid amount.",
  "city.request.notonserver": "§cThat player is not on this server.",
  "city.request.sent": "§aPayment request sent to §e{0}§a.",
  "city.request.notenough": "§cYou do not have enough Shards to fulfill this request.",
  "city.request.failed.notenough": "§c{0} does not have enough Shards.",
  "city.request.paid.self": "§aYou have paid §u{0} Shards §ato §e{1}§a.",
  "city.request.paid.other": "§a{0} §apaid §u{1} Shards§a.",
  "city.request.declined.self": "§7You have declined the request.",
  "city.request.declined.other": "§e{0} §7has declined the request.",
  "city.request.notify": "§e{0} §7sent you a payment request for §u{1} Shards§7. Open §e/invoice §7to view it.",
  "city.invoice.title": "§l§6Payment Requests",
  "city.invoice.content": "§7Select a request.",
  "city.invoice.list.entry": "§e{0}\n§7Amount: §u{1}",
  "city.invoice.detail.title": "§l§6Request Details",
  "city.invoice.detail.requester": "§bFrom: §e{0}",
  "city.invoice.detail.amount": "§bAmount: §e{0}",
  "city.invoice.detail.note": "§bNote: {0}",
  "city.invoice.detail.date": "§bTime: §e{0}",
  "city.invoice.button.pay": "Pay",
  "city.invoice.button.decline": "Decline",
  "city.invoice.invalid": "§cThis request is no longer valid.",
  "commands.auctionhouse.description": "Open Auction House",
  "commands.auctionhouse.usage": "/auctionhouse",
  "commands.back.description": "Return to your last location",
  "commands.back.usage": "/back",
  "commands.backpack.description": "Open backpack",
  "commands.backpack.usage": "/backpack",
  "commands.bank.description": "Manage bank accounts",
  "commands.bank.usage": "/bank",
  "commands.bankadmin.description": "Manage bank accounts (Admin)",
  "commands.bankadmin.usage": "/bankadmin",
  "commands.clear.description": "Clear inventory",
  "commands.clear.usage": "/clear",
  "commands.clearchat.description": "Clear chat",
  "commands.clearchat.usage": "/clearchat",
  "commands.ecoaudit.description": "View economy audit log",
  "commands.ecoaudit.usage": "/ecoaudit",
  "commands.farmitems.description": "Submit farm items",
  "commands.farmitems.usage": "/farmitems",
  "commands.feed.description": "Restore hunger",
  "commands.feed.usage": "/feed",
  "commands.fix.description": "Repair inventory or chunks",
  "commands.fix.usage": "/fix [chunks|inv]",
  "commands.fly.description": "Toggle fly mode",
  "commands.fly.usage": "/fly",
  "commands.flytime.description": "Grant flight time (Admin)",
  "commands.flytime.usage": "/flytime [player] [minutes]",
  "commands.heal.description": "Restore health",
  "commands.heal.usage": "/heal",
  "commands.home.description": "Manage or teleport to a home",
  "commands.home.usage": "/home [name]",
  "commands.sethome.description": "Set a home",
  "commands.sethome.usage": "/sethome <name>",
  "commands.idcardgive.description": "Give an ID card",
  "commands.idcardgive.usage": "/idcardgive <player>",
  "commands.inventorysee.description": "View a player's inventory",
  "commands.inventorysee.usage": "/invsee <player> [type]",
  "commands.invoice.description": "View payment requests",
  "commands.invoice.usage": "/invoice",
  "commands.jobs.description": "Manage jobs",
  "commands.jobs.usage": "/jobs",
  "commands.marketvalue.description": "View market values",
  "commands.marketvalue.usage": "/marketvalue",
  "commands.pay.description": "Send Shards to a player",
  "commands.pay.usage": "/pay",
  "commands.requestmoney.description": "Request a payment",
  "commands.requestmoney.usage": "/requestmoney",
  "commands.sb.description": "Scoreboard settings",
  "commands.sb.usage": "/sb",
  "commands.shopfinder.description": "Open Shop Finder",
  "commands.shopfinder.usage": "/shopfinder",
  "commands.trade.description": "Request a trade",
  "commands.trade.usage": "/trade <player>",
  "commands.train.description": "Open train controls",
  "commands.train.usage": "/train",
  "commands.wallet.description": "View wallet",
  "commands.wallet.usage": "/wallet [player]",
  "commands.isle.description": "Isle management",
  "commands.isle.usage": "/isle",
  "commands.property.description": "Manage plot",
  "commands.property.usage": "/property"
}